README.txt
setup.py
pydatabase/__init__.py
pydatabase/databasecolumn.py
pydatabase/databaseconnection.py
pydatabase/databasetable.py
pydatabase/query.py
pydatabase/selectquery.py
pydatabase.egg-info/PKG-INFO
pydatabase.egg-info/SOURCES.txt
pydatabase.egg-info/dependency_links.txt
pydatabase.egg-info/requires.txt
pydatabase.egg-info/top_level.txt