Metadata-Version: 1.0
Name: pydatabase
Version: 1.0.2
Summary: Simple interface for MySQL databases
Home-page: http://pydatabase.lukeshiner.com
Author: Luke Shiner
Author-email: luke@lukeshiner.com
License: UNKNOWN
Keywords: database,mysql,simple
Platform: UNKNOWN
